transcv/__init__.py
transcv/_nbdev.py
transcv/detr.py
transcv/swin.py
transcv/visrectrans.py
transcv-0.0.5.dist-info/LICENSE
transcv-0.0.5.dist-info/METADATA
transcv-0.0.5.dist-info/WHEEL
transcv-0.0.5.dist-info/entry_points.txt
transcv-0.0.5.dist-info/top_level.txt
transcv-0.0.5.dist-info/RECORD
