Metadata-Version: 2.1
Name: transcv
Version: 0.0.5
Summary: A library for creating vision transformers for computer vision
Home-page: https://github.com/Ys-Prakash/transcv/tree/master/
Author: Prakash Pandey
Author-email: prapandey03@gmail.com
License: Apache Software License 2.0
Keywords: transcv fastai Vit detr
Platform: UNKNOWN
Classifier: Development Status :: 3 - Alpha
Classifier: Intended Audience :: Developers
Classifier: Natural Language :: English
Classifier: Programming Language :: Python :: 3.6
Classifier: Programming Language :: Python :: 3.7
Classifier: Programming Language :: Python :: 3.8
Classifier: License :: OSI Approved :: Apache Software License
Requires-Python: >=3.6
Requires-Dist: pip
Requires-Dist: packaging
Requires-Dist: fastai
Requires-Dist: timm
Requires-Dist: transformers[sentencepiece]
Provides-Extra: dev
